ch340_nrf/__init__.py
ch340_nrf/nrf.py
ch340_nrf/requirements.txt
ch340_nrf/translator.py
ch340_nrf-0.1.4.dist-info/METADATA
ch340_nrf-0.1.4.dist-info/WHEEL
ch340_nrf-0.1.4.dist-info/licenses/LICENSE
ch340_nrf-0.1.4.dist-info/RECORD
