Metadata-Version: 2.1
Name: ch340_nrf
Version: 0.1.4
Summary: Allows you to use the ch340 nrf usb adapter with python. This project is currently in developement.
Project-URL: Homepage, https://github.com/drakeerv/ch340_nrf
Project-URL: Bug Tracker, https://github.com/drakeerv/ch340_nrf/issues
Author-email: drakeerv <drakeerv@outlook.com>
License-File: LICENSE
Classifier: Development Status :: 3 - Alpha
Classifier: Intended Audience :: Developers
Classifier: License :: OSI Approved :: MIT License
Classifier: Natural Language :: English
Classifier: Operating System :: MacOS :: MacOS X
Classifier: Operating System :: Microsoft :: Windows
Classifier: Operating System :: POSIX
Classifier: Programming Language :: Python :: 3
Classifier: Topic :: Communications
Classifier: Topic :: Software Development :: Libraries
Classifier: Topic :: Software Development :: Libraries :: Python Modules
Classifier: Topic :: Terminals :: Serial
Requires-Python: >=3.0
Requires-Dist: pyserial
